{
  "$schema": "https://raw.githubusercontent.com/OpenLightingProject/open-fixture-library/master/schemas/fixture.json",
  "name": "Thunder Wash 100 RGB (6ch mode)",
  "shortName": "CLTW100RGB-6ch",
  "categories": ["Other"],
  "meta": {
    "authors": ["Felix Edelmann"],
    "createDate": "2017-02-24",
    "lastModifyDate": "2017-03-09",
    "importPlugin": {
      "plugin": "ecue",
      "date": "2018-09-11"
    }
  },
  "comment": "generated by the Open Fixture Library – https://open-fixture-library.herokuapp.com/cameo/thunder-wash-100-rgb",
  "physical": {
    "dimensions": [310, 70, 70],
    "weight": 1,
    "power": 30
  },
  "availableChannels": {
    "Dimmer": {
      "highlightValue": 255,
      "capability": {
        "type": "Intensity"
      }
    },
    "Strobe": {
      "highlightValue": 220,
      "capabilities": [
        {
          "dmxRange": [0, 5],
          "type": "ShutterStrobe",
          "shutterEffect": "Strobe",
          "comment": "Strobe open"
        },
        {
          "dmxRange": [6, 10],
          "type": "ShutterStrobe",
          "shutterEffect": "Strobe",
          "comment": "Strobe closed"
        },
        {
          "dmxRange": [11, 33],
          "type": "ShutterStrobe",
          "shutterEffect": "PulseRandom",
          "speedStart": "slow",
          "speedEnd": "fast",
          "comment": "Puls random",
          "menuClick": "center"
        },
        {
          "dmxRange": [34, 56],
          "type": "ShutterStrobe",
          "shutterEffect": "RampUpRandom",
          "speedStart": "slow",
          "speedEnd": "fast",
          "comment": "Ramp up random",
          "menuClick": "center"
        },
        {
          "dmxRange": [57, 79],
          "type": "ShutterStrobe",
          "shutterEffect": "RampDownRandom",
          "speedStart": "slow",
          "speedEnd": "fast",
          "comment": "Ramp down random",
          "menuClick": "center"
        },
        {
          "dmxRange": [80, 102],
          "type": "ShutterStrobe",
          "shutterEffect": "StrobeRandom",
          "speedStart": "slow",
          "speedEnd": "fast",
          "comment": "Random Strobe Effect",
          "menuClick": "center"
        },
        {
          "dmxRange": [103, 127],
          "type": "ShutterStrobe",
          "shutterEffect": "Strobe",
          "comment": "Strobe Break Effect 5s-1s",
          "menuClick": "center"
        },
        {
          "dmxRange": [128, 250],
          "type": "ShutterStrobe",
          "shutterEffect": "Strobe",
          "speedStart": "0Hz",
          "speedEnd": "30Hz",
          "menuClick": "center"
        },
        {
          "dmxRange": [251, 255],
          "type": "ShutterStrobe",
          "shutterEffect": "Strobe",
          "comment": "Strobe open",
          "menuClick": "hidden"
        }
      ]
    },
    "Red": {
      "highlightValue": 255,
      "capability": {
        "type": "ColorIntensity",
        "color": "Red"
      }
    },
    "Green": {
      "highlightValue": 255,
      "capability": {
        "type": "ColorIntensity",
        "color": "Green"
      }
    },
    "Blue": {
      "highlightValue": 255,
      "capability": {
        "type": "ColorIntensity",
        "color": "Blue"
      }
    },
    "Sound Control": {
      "highlightValue": 255,
      "capabilities": [
        {
          "dmxRange": [0, 5],
          "type": "Generic",
          "comment": "Sound Control Off"
        },
        {
          "dmxRange": [6, 255],
          "type": "SoundSensitivity",
          "comment": "Mic Sensitivity Low-High",
          "menuClick": "center"
        }
      ]
    }
  },
  "modes": [
    {
      "name": "6-channel",
      "shortName": "6ch",
      "channels": [
        "Dimmer",
        "Strobe",
        "Red",
        "Green",
        "Blue",
        "Sound Control"
      ]
    }
  ]
}
